aiocsv/__init__.py
aiocsv/_parser.c
aiocsv/_parser.cp314t-win_amd64.pyd
aiocsv/_parser.pyi
aiocsv/parser.py
aiocsv/protocols.py
aiocsv/py.typed
aiocsv/readers.py
aiocsv/writers.py
aiocsv-1.4.0.dist-info/licenses/LICENSE
aiocsv-1.4.0.dist-info/METADATA
aiocsv-1.4.0.dist-info/WHEEL
aiocsv-1.4.0.dist-info/top_level.txt
aiocsv-1.4.0.dist-info/RECORD
