Metadata-Version: 2.4
Name: aiocsv
Version: 1.4.0
Author-email: Mikołaj Kuranowski <mkuranowski+pypackages@gmail.com>
Project-URL: Homepage, https://github.com/MKuranowski/aiocsv
Keywords: async,asynchronous,csv,tsv
Classifier: Development Status :: 5 - Production/Stable
Classifier: License :: OSI Approved :: MIT License
Classifier: Framework :: AsyncIO
Classifier: Programming Language :: Python :: 3 :: Only
Requires-Python: >=3.9
License-File: LICENSE
Requires-Dist: typing_extensions
Dynamic: license-file
